{"trial_id": "3", "hyperparameters": {"space": [{"class_name": "Choice", "config": {"name": "lstm_units", "default": 32, "conditions": [], "values": [32, 64, 128], "ordered": true}}, {"class_name": "Choice", "config": {"name": "dropout", "default": 0.2, "conditions": [], "values": [0.2, 0.3, 0.5], "ordered": true}}, {"class_name": "Choice", "config": {"name": "learning_rate", "default": 0.001, "conditions": [], "values": [0.001, 0.0001], "ordered": true}}], "values": {"lstm_units": 128, "dropout": 0.2, "learning_rate": 0.0001}}, "metrics": {"metrics": {"loss": {"direction": "min", "observations": [{"value": [3814.108642578125], "step": 99}]}, "mae": {"direction": "min", "observations": [{"value": [21.39556884765625], "step": 99}]}, "val_loss": {"direction": "min", "observations": [{"value": [4117.00341796875], "step": 99}]}, "val_mae": {"direction": "min", "observations": [{"value": [24.796676635742188], "step": 99}]}, "learning_rate": {"direction": "min", "observations": [{"value": [6.24999984211172e-06], "step": 99}]}}}, "score": 4117.00341796875, "best_step": 99, "status": "COMPLETED", "message": null}